ploft/__init__.py
ploft/jsc/main2.js
ploft/jsc/main4.js
ploft-0.0.13.dist-info/METADATA
ploft-0.0.13.dist-info/WHEEL
ploft-0.0.13.dist-info/top_level.txt
ploft-0.0.13.dist-info/RECORD
