Metadata-Version: 2.1
Name: ploft
Version: 0.0.13
Summary: Data Visualization
Author-email: Christoph Chester Cury <cury.grupos@gmail.com>
License: MIT
Classifier: Programming Language :: Python :: 3
Classifier: License :: OSI Approved :: MIT License
Classifier: Operating System :: OS Independent
Requires-Python: >=3.6
